{
    "key": "group_55e79e3e4cf55",
    "title": "Page \u2014 Home |\u00a0Aktuell",
    "fields": [
        {
            "key": "field_55e79e490fa48",
            "label": "Please Note!",
            "name": "",
            "type": "message",
            "instructions": "",
            "required": 0,
            "conditional_logic": 0,
            "wrapper": {
                "width": "",
                "class": "",
                "id": ""
            },
            "message": "All settings of the home page can be found in options page <a href=\"admin.php?page=site-settings\"><strong>Details<\/strong><\/a>.",
            "esc_html": 0
        }
    ],
    "location": [
        [
            {
                "param": "page_template",
                "operator": "==",
                "value": "page-home.php"
            }
        ]
    ],
    "menu_order": 0,
    "position": "normal",
    "style": "seamless",
    "label_placement": "top",
    "instruction_placement": "label",
    "hide_on_screen": [
        "the_content"
    ],
    "active": 1,
    "description": "",
    "modified": 1441244165
}